[{"date":"2018-12-24T15:16:38","slug":"updating-a-cypress-alias","title":"Updating a Cypress alias"},{"date":"2018-04-25T19:36:08","slug":"javascript-generators-iterators-use-case","title":"A use case for Javascript generators"},{"date":"2018-03-03T01:00:14","slug":"project-invoice","title":"Project invoice"},{"date":"2017-08-09T20:45:25","slug":"best-free-editor-on-android","title":"The best programming editor on Android is free"},{"date":"2017-08-02T08:59:52","slug":"experiment-marbles","title":"Experiment: marbles"},{"date":"2017-07-12T19:40:59","slug":"pixel-perfect-bookmarklet","title":"Pixel perfect bookmarklet"},{"date":"2017-01-28T07:58:10","slug":"vue-js-timing-hack-component-transitions","title":"A Vue.js timing hack in component transitions"},{"date":"2017-01-24T15:30:55","slug":"experiment-fire","title":"Experiment: procedural fire with sparks in glsl"},{"date":"2017-01-14T10:07:46","slug":"experiment-spiralmap","title":"Experiment: spiral map"},{"date":"2017-01-08T11:19:03","slug":"experiment-clouds","title":"Experiment: clouds"},{"date":"2016-12-24T08:49:00","slug":"wordpress-rest-api-using-vue-webpack","title":"WordPress with a REST API using Vue and Webpack"},{"date":"2016-11-26T09:54:11","slug":"angular-two-versus-vue","title":"Angular 2 or Vue"},{"date":"2016-09-06T15:06:00","slug":"experiment-radialdifference","title":"Experiment: difference with radial gradients in canvas"},{"date":"2016-04-13T20:14:49","slug":"strange-attractors-javascript","title":"Strange attractors in Javascript"},{"date":"2015-11-03T08:09:00","slug":"memory-and-speed-performance-of-different-namespace-patterns","title":"Memory and speed performance of different namespace patterns"},{"date":"2015-10-25T07:22:25","slug":"experiment-blob","title":"Experiment: webgl blob"},{"date":"2015-10-22T20:40:18","slug":"how-to-structure-javascript-code-within-a-closure-in-a-logical-way","title":"How to structure Javascript code within a closure in a logical way"},{"date":"2015-02-19T19:14:01","slug":"javascript-inheritance-protected-methods","title":"Javascript inheritance and protected methods"},{"date":"2015-01-28T12:24:12","slug":"lorem-ipsum-dummy-article-shortcode-plugin","title":"Lorem ipsum dummy article shortcode plugin"},{"date":"2015-01-24T21:13:30","slug":"goodbye-sjeiti-com","title":"Goodbye sjeiti.com"},{"date":"2015-01-05T10:02:05","slug":"tinysort-v2","title":"Tinysort v2"},{"date":"2014-11-11T12:21:49","slug":"strong-password-generator-bookmarklet","title":"Strong password generator bookmarklet generator"},{"date":"2014-08-26T18:17:47","slug":"experiment-voronoi","title":"Experiment: Voronoi"},{"date":"2014-06-22T15:25:56","slug":"experiment-glass","title":"Experiment: glass"},{"date":"2014-06-11T17:05:40","slug":"wordpress-pocket-widget","title":"WordPress Pocket widget"},{"date":"2014-05-26T10:34:38","slug":"dry-responsive-javascript","title":"DRY responsive Javascript"},{"date":"2014-05-10T11:10:39","slug":"using-google-spreadsheets-for-invoicing","title":"Using Google spreadsheets for your freelance invoicing"},{"date":"2014-05-06T20:58:18","slug":"change-css-styles-at-the-root","title":"Change CSS styles at the root."},{"date":"2014-04-26T19:37:36","slug":"experiment-snow","title":"Experiment: snow"},{"date":"2014-04-24T11:19:04","slug":"experiment-vertical","title":"Experiment: vertical"},{"date":"2014-04-24T11:19:04","slug":"experiment-touches","title":"Experiment: touches"},{"date":"2014-04-24T11:19:04","slug":"experiment-starzoom","title":"Experiment: starzoom"},{"date":"2014-04-24T11:19:04","slug":"experiment-plasma","title":"Experiment: plasma"},{"date":"2014-04-24T11:19:04","slug":"experiment-grid","title":"Experiment: grid"},{"date":"2014-04-24T11:19:04","slug":"experiment-flowfield","title":"Experiment: flow field"},{"date":"2014-04-24T11:19:03","slug":"experiment-ff","title":"Experiment: ff"},{"date":"2014-04-22T15:38:25","slug":"experiment-boids","title":"Experiment: boids"},{"date":"2014-01-22T15:42:48","slug":"experiment-heart","title":"Experiment: heart"},{"date":"2013-08-08T12:48:56","slug":"testing-for-unused-functions-with-grunt","title":"Testing for unused functions with Grunt"},{"date":"2013-05-29T09:53:26","slug":"a-freelance-developers-tool-box","title":"A freelance developer&#8217;s tool box"},{"date":"2013-04-07T11:08:55","slug":"bookmarklet-for-fullscreen-google-maps","title":"Bookmarklet for fullscreen Google Maps"},{"date":"2013-01-22T14:37:43","slug":"multiple-properties-in-one-variable","title":"Storing multiple properties in one integer using bitwise AND"},{"date":"2012-09-26T11:11:32","slug":"creating-tileable-noise-maps","title":"Creating tileable noise maps"},{"date":"2012-08-24T11:16:27","slug":"migrating-a-subversion-repository-from-google-code-to-github","title":"Migrating a subversion repository from Google Code to Github"},{"date":"2012-07-06T17:45:45","slug":"logo","title":"Logo"},{"date":"2012-07-03T07:46:41","slug":"tinysort-a-tiny-survey","title":"Tinysort: a tiny survey"},{"date":"2012-06-30T11:30:27","slug":"android-phone-dom","title":"Android phone DOM"},{"date":"2012-06-28T16:40:08","slug":"test-rainbow","title":"Test Rainbow line numbering"},{"date":"2012-06-18T15:01:18","slug":"less-variables-to-javascript","title":"LESS variables to Javascript"},{"date":"2012-05-25T12:47:34","slug":"interactive-fluid-dynamics-in-javascript","title":"Interactive fluid dynamics in Javascript"},{"date":"2012-05-01T21:42:37","slug":"using-wordpress-media-library-in-a-plugin","title":"Using WordPress media library in a plugin"},{"date":"2012-04-25T20:59:00","slug":"javascript-performance-testing","title":"Javascript performance testing"},{"date":"2012-02-14T23:26:43","slug":"js1k","title":"JS1k"},{"date":"2012-01-31T13:47:35","slug":"unit-testing-private-functions","title":"Unit testing private functions in Javascript"},{"date":"2012-01-30T13:41:24","slug":"873","title":""},{"date":"2011-06-03T00:12:36","slug":"dynamic-bookmarklets-and-webgl","title":"Dynamic bookmarklets (and WebGL)"},{"date":"2011-04-09T00:24:10","slug":"it-could-be-dawn","title":"It could be dawn"},{"date":"2011-04-09T00:17:59","slug":"sfbrowser-3-2-2","title":"SFBrowser 3.2.2"},{"date":"2011-02-02T23:39:45","slug":"witnie-in-the-sky-with-diamonds","title":"Witnie in the sky with diamonds"},{"date":"2011-02-02T10:56:35","slug":"pig-in-woods","title":"Pig in woods"},{"date":"2010-11-19T02:38:25","slug":"sfbrowser-for-wordpress","title":"SFBrowser for WordPress"},{"date":"2010-10-22T13:14:15","slug":"canvasimg","title":"canvasImg"},{"date":"2010-10-22T13:07:44","slug":"perpetuum-mobile","title":"perpetuum mobile"},{"date":"2010-09-17T14:17:38","slug":"stereoscopic-3d-zoom-with-javascript","title":"Stereoscopic 3D zoom with Javascript"},{"date":"2010-09-13T18:41:39","slug":"coding-on-an-android","title":"coding on an android"},{"date":"2010-07-22T21:38:36","slug":"meten-is-weten","title":"meten is weten"},{"date":"2010-06-02T10:33:04","slug":"emergence","title":"emergence"},{"date":"2010-05-13T22:49:36","slug":"simplex-noise-in-as3","title":"Simplex noise in as3"},{"date":"2010-05-12T14:05:05","slug":"perlin-noise-versus-simplex-noise-in-javascript-final-comparison","title":"Perlin noise versus Simplex noise in Javascript (final comparison)"},{"date":"2010-05-10T13:39:54","slug":"perlin-noise-in-javascript-comparisons","title":"Perlin noise in Javascript comparisons"},{"date":"2010-05-04T14:45:21","slug":"freelance-space-for-hire","title":"freelance space for hire"},{"date":"2010-03-06T11:33:35","slug":"twitter","title":"Twitter"},{"date":"2010-02-13T19:01:37","slug":"icon-for-new-jquery-plugin","title":"icon for new jQuery plugin"},{"date":"2010-01-27T12:03:11","slug":"cleanup","title":"cleanup"},{"date":"2009-12-17T16:11:38","slug":"android-processing","title":"Android Processing"},{"date":"2009-09-18T02:21:43","slug":"gridfeed","title":"jQuery.feedQuilt"},{"date":"2009-07-13T17:54:06","slug":"woot-fwa-sotd","title":"WOOT FWA SOTD!!!"},{"date":"2009-07-07T14:52:31","slug":"html5","title":"HTML5"},{"date":"2009-02-28T00:00:29","slug":"perlin-clouds","title":"Perlin clouds"},{"date":"2009-02-19T12:23:00","slug":"learning-a-new-language","title":"learning a new language"},{"date":"2009-01-29T16:10:23","slug":"ronvalstarnl","title":"localhost.ronvalstar"},{"date":"2008-12-31T11:56:53","slug":"sfbrowser-3-beta","title":"SFBrowser 3 beta"},{"date":"2008-12-13T19:58:42","slug":"attractors-rebuild","title":"Attractors rebuild"},{"date":"2008-12-13T16:13:04","slug":"sfbrowsergooglecode","title":"sfbrowser.googlecode"},{"date":"2008-11-22T21:07:44","slug":"331","title":"jQuery plugin update"},{"date":"2008-10-06T16:11:43","slug":"workplace-for-hire","title":"workplace for hire"},{"date":"2008-07-31T17:10:33","slug":"perlin-noise-and-frocessing","title":"Perlin Noise and Frocessing"},{"date":"2008-06-30T14:46:49","slug":"processingjs","title":"Processing.js"},{"date":"2008-06-29T12:16:32","slug":"sfbrowser","title":"SFBrowser"},{"date":"2008-06-19T13:17:28","slug":"hyves-redesign","title":"Hyves redesign"},{"date":"2008-06-08T21:46:24","slug":"jquerytinysort","title":"jquery.tinysort"},{"date":"2008-06-08T20:09:51","slug":"tinysort","title":"TinySort"},{"date":"2008-06-02T16:54:59","slug":"psp-e-books-ii","title":"PSP e-books"},{"date":"2008-06-02T15:16:51","slug":"e-books-on-your-psp","title":"E-books on your PSP"},{"date":"2008-02-16T14:14:53","slug":"48-hours-of-rendering","title":"48 hours of rendering"},{"date":"2008-02-13T20:08:50","slug":"strange-attractors","title":"Protected: Strange attractors"},{"date":"2008-02-10T22:26:46","slug":"strange-stuff","title":"Strange stuff"},{"date":"2008-02-10T01:40:28","slug":"lorenz84","title":"Lorenz84"},{"date":"2007-12-23T19:56:43","slug":"little-fluffy-clouds","title":"little fluffy clouds"},{"date":"2007-12-17T19:47:04","slug":"whooohooo","title":"Whooohooo"},{"date":"2007-12-14T22:39:00","slug":"papervision3d-2-alpha","title":"PaperVision3D 2 alpha"},{"date":"2007-11-25T19:44:41","slug":"psp-as-e-book","title":"PSP as e-book"},{"date":"2007-11-09T17:01:42","slug":"flash-plugin-bug","title":"Flash plugin bug"},{"date":"2007-11-02T00:42:31","slug":"as3-or-p55","title":"as3 or p55"},{"date":"2007-10-04T00:06:33","slug":"perlin-noise-in-as3","title":"Perlin noise in as3"},{"date":"2007-10-01T23:44:39","slug":"brokenfixed","title":"broken/fixed"},{"date":"2007-09-19T13:49:51","slug":"algorithmic-botany","title":"Algorithmic botany"},{"date":"2007-09-17T18:36:07","slug":"subtitles","title":"subtitles"},{"date":"2007-07-26T18:43:35","slug":"free","title":"free"},{"date":"2007-05-21T21:30:21","slug":"cubejunky","title":"cubejunky"},{"date":"2007-04-26T08:21:09","slug":"jquery","title":"jquery"},{"date":"2007-04-15T21:07:43","slug":"amfphp-and-as3","title":"amfphp and as3"},{"date":"2007-03-29T15:27:53","slug":"illustration","title":"illustration"},{"date":"2007-03-05T21:41:21","slug":"filter-forge-released","title":"Filter Forge released"},{"date":"2007-03-05T12:16:54","slug":"terraforming","title":"terraforming"},{"date":"2007-02-24T19:37:19","slug":"papervision3d","title":"Papervision3D"},{"date":"2007-02-17T23:24:00","slug":"dhtml-list-fold","title":"javascript unordered list folding"},{"date":"2007-02-15T23:39:18","slug":"beta-testing-rocks","title":"beta testing rocks"},{"date":"2007-02-13T23:25:20","slug":"2007","title":"2007"},{"date":"2007-02-12T16:15:49","slug":"updated-plugins","title":"updated plugins"},{"date":"2007-01-31T19:38:56","slug":"faking-cron-jobs-for-sparklines","title":"faking cron jobs for sparklines"},{"date":"2007-01-31T18:29:19","slug":"wordpress-plugin-cronfaker","title":"Cronfaker plugin"},{"date":"2007-01-28T14:17:07","slug":"librarything-widget","title":"Librarything widget"},{"date":"2007-01-28T13:11:15","slug":"wordpress-plugin-librarything-widget","title":"Librarything widget"},{"date":"2007-01-23T10:13:39","slug":"wordpress-plugin-stats","title":"Stats plugin"},{"date":"2007-01-23T10:10:37","slug":"plugins","title":"plugins"},{"date":"2007-01-19T01:57:10","slug":"wordpress","title":"WordPress"},{"date":"2007-01-07T17:11:46","slug":"starfield","title":"starfield"},{"date":"2007-01-07T12:45:18","slug":"tissue","title":"living tissue"},{"date":"2007-01-07T12:44:51","slug":"growth","title":"growth"},{"date":"2007-01-07T12:44:34","slug":"ny2004","title":"2004"},{"date":"2007-01-07T12:44:19","slug":"cells","title":"cells"},{"date":"2007-01-07T12:44:04","slug":"magnetic","title":"magnetic particles"},{"date":"2007-01-07T12:43:34","slug":"grass","title":"grass"},{"date":"2007-01-07T12:43:20","slug":"noise-grid","title":"noise grid"},{"date":"2007-01-07T12:42:55","slug":"hypnosis","title":"hypnosis"},{"date":"2007-01-07T12:42:28","slug":"landscapes","title":"landscapes"},{"date":"2007-01-07T12:42:03","slug":"patternation","title":"patternation"},{"date":"2007-01-07T12:41:34","slug":"attractor","title":"attractor viewer"},{"date":"2007-01-02T22:40:59","slug":"youtubeprocessinggroup","title":"Youtube Processing group"},{"date":"2006-11-12T22:56:17","slug":"juridacom","title":"Jurida.com"},{"date":"2006-10-07T00:26:58","slug":"komkommertijd","title":"Komkommertijd"},{"date":"2006-07-19T08:48:25","slug":"pspbrowsing","title":"PSP browsing"},{"date":"2006-07-09T00:50:41","slug":"comicomaticupdate","title":"comic.o.matic update"},{"date":"2006-06-28T10:34:56","slug":"brevity","title":"Brevity?!"},{"date":"2006-06-23T23:10:34","slug":"justsomeflvtests","title":"just some flv tests"},{"date":"2006-06-18T01:00:06","slug":"librarything","title":"librarything"},{"date":"2006-06-11T10:38:15","slug":"stripomatic","title":"strip.o.matic"},{"date":"2006-06-01T16:26:54","slug":"filterforge","title":"Filter Forge"},{"date":"2006-05-31T15:40:07","slug":"kleurenspeuren","title":"kleuren speuren"},{"date":"2006-05-29T22:21:47","slug":"irrepressible","title":"irrepressible"},{"date":"2006-04-11T10:19:54","slug":"knikkertijd-2","title":"knikkertijd"},{"date":"2006-02-08T13:54:46","slug":"restyle","title":"restyle"},{"date":"2006-01-24T15:57:36","slug":"knikkertijd","title":"knikkertijd"},{"date":"2006-01-07T22:43:27","slug":"yummy","title":"yummy"},{"date":"2006-01-01T22:58:50","slug":"delicious","title":"Delicious"},{"date":"2005-12-27T10:15:55","slug":"sparklines","title":"sparklines"},{"date":"2005-12-23T23:29:47","slug":"merrychristmasandahappynewyear","title":"merry christmas and a happy newyear"},{"date":"2005-11-24T00:23:48","slug":"gddiagrams","title":"gd diagrams"},{"date":"2005-10-27T19:22:07","slug":"sjeitiv15","title":"Sjeiti v15"},{"date":"2005-09-20T22:20:48","slug":"recursion","title":"recursion"},{"date":"2005-06-23T16:04:58","slug":"sheep","title":"sheep"},{"date":"2005-05-20T20:47:51","slug":"screensaver","title":"screensaver"},{"date":"2005-04-29T11:20:08","slug":"strangepeople","title":"strange people"},{"date":"2005-03-19T10:58:24","slug":"movies","title":"movies"},{"date":"2005-03-12T01:06:18","slug":"attractorviewer","title":"attractorViewer"},{"date":"2005-03-03T10:11:06","slug":"johncoltrane","title":"John Coltrane"},{"date":"2005-03-02T11:34:49","slug":"galaxies","title":"galaxies"},{"date":"2005-02-25T11:37:30","slug":"erased","title":"erased"},{"date":"2005-02-20T22:13:23","slug":"art","title":"art"},{"date":"2005-02-12T12:36:20","slug":"referer","title":"referer"},{"date":"2005-01-28T03:06:09","slug":"littlegame","title":"little game"},{"date":"2005-01-16T02:49:26","slug":"linksubmission","title":"link submission"},{"date":"2004-12-23T19:05:15","slug":"happynewyear","title":"happy newyear"},{"date":"2004-12-09T10:14:05","slug":"links","title":"links"},{"date":"2004-11-13T18:36:27","slug":"ehm","title":"ehm"},{"date":"2004-10-20T06:12:53","slug":"change","title":"change"},{"date":"2004-10-07T02:24:55","slug":"sketches","title":"sketches"},{"date":"2004-10-02T18:13:39","slug":"randomlink","title":"randomlink"},{"date":"2004-10-01T18:12:27","slug":"rss-2","title":"rss"},{"date":"2004-09-17T18:03:40","slug":"images","title":"images"},{"date":"2004-07-16T21:57:38","slug":"labgame","title":"labgame"},{"date":"2004-07-03T03:06:56","slug":"immortel","title":"immortel"},{"date":"2004-06-23T21:04:12","slug":"shockwave","title":"shockwave"},{"date":"2004-06-16T22:36:26","slug":"php-finally","title":"php"},{"date":"2004-04-21T18:40:10","slug":"pfff","title":"pfff"},{"date":"2004-03-17T17:54:20","slug":"sound","title":"sound"},{"date":"2004-03-03T10:51:13","slug":"relkanoid","title":"relkanoid"},{"date":"2004-01-17T16:41:20","slug":"magnet","title":"magnet"},{"date":"2004-01-05T18:56:48","slug":"patterngenerator","title":"pattern generator"},{"date":"2003-12-24T03:11:47","slug":"scans","title":"scans"},{"date":"2003-12-01T11:32:02","slug":"frontpage","title":"frontpage"},{"date":"2003-12-01T03:42:32","slug":"redesign-2","title":"redesign"},{"date":"2003-10-17T10:40:19","slug":"added","title":"added"},{"date":"2003-10-16T13:56:39","slug":"268","title":"…"},{"date":"2003-10-08T08:18:41","slug":"269","title":"?"},{"date":"2003-09-30T02:57:41","slug":"redesign","title":"redesign"},{"date":"2003-09-12T18:17:00","slug":"271","title":":-("}]